xontrib_commands/__init__.py
xontrib_commands/argerize.py
xontrib_commands/cmds/__init__.py
xontrib_commands/cmds/dev_cmd.py
xontrib_commands/cmds/dotenv_cmd.py
xontrib_commands/cmds/parallex.py
xontrib_commands/cmds/reload.py
xontrib_commands/cmds/report_keys.py
xontrib_commands/main.py
xontrib_commands/utils.py
xontrib_commands-0.4.4.dist-info/entry_points.txt
xontrib_commands-0.4.4.dist-info/WHEEL
xontrib_commands-0.4.4.dist-info/METADATA
xontrib_commands-0.4.4.dist-info/licenses/LICENSE
xontrib_commands-0.4.4.dist-info/RECORD
