Metadata-Version: 2.1
Name: xontrib-commands
Version: 0.4.4
Summary: Useful xonsh-shell commands/alias functions
License: MIT
Keywords: xontrib,xonsh
Author-email: Noortheen Raja NJ <jnoortheen@gmail.com>
Requires-Python: >=3.8
Classifier: Intended Audience :: Developers
Classifier: License :: OSI Approved :: MIT License
Classifier: Natural Language :: English
Classifier: Operating System :: OS Independent
Classifier: Programming Language :: Python
Classifier: Programming Language :: Python :: 3
Classifier: Topic :: System :: Shells
Classifier: Topic :: System :: System Shells
Classifier: Topic :: Terminals
Requires-Dist: arger>=1.2.7; python_version >= "3.6" and python_version < "4.0"
Requires-Dist: python-dotenv>=0.19.1
Requires-Dist: rich; python_version >= "3.6" and python_version < "4.0"
Requires-Dist: xonsh>=0.12.5
Provides-Extra: dev
Requires-Dist: pytest; extra == "dev"
Requires-Dist: black; extra == "dev"
Project-URL: Code, https://github.com/jnoortheen/xontrib-commands
Project-URL: Documentation, https://github.com/jnoortheen/xontrib-commands/blob/master/README.md
Project-URL: Issue tracker, https://github.com/jnoortheen/xontrib-commands/issues
Project-URL: repository, https://github.com/jnoortheen/xontrib-commands
